jovyanai_extension/__init__.py
jovyanai_extension/_version.py
jovyanai_extension/cli.py
jovyanai_extension/extension.py
jovyanai_extension/handlers.py
jovyanai_extension/labextension/package.json
jovyanai_extension-0.3.1.data/data/etc/jupyter/jupyter_server_config.d/jovyanai_extension.json
jovyanai_extension-0.3.1.data/data/share/jupyter/labextensions/@jovyanai/labextension/package.json
jovyanai_extension-0.3.1.data/data/share/jupyter/labextensions/@jovyanai/labextension/schemas/@jovyanai/labextension/package.json.orig
jovyanai_extension-0.3.1.data/data/share/jupyter/labextensions/@jovyanai/labextension/schemas/@jovyanai/labextension/plugin.json
jovyanai_extension-0.3.1.data/data/share/jupyter/labextensions/@jovyanai/labextension/static/112.1840b7871679481376da.js
jovyanai_extension-0.3.1.data/data/share/jupyter/labextensions/@jovyanai/labextension/static/146.31057e7ffbc427828fa9.js
jovyanai_extension-0.3.1.data/data/share/jupyter/labextensions/@jovyanai/labextension/static/146.31057e7ffbc427828fa9.js.LICENSE.txt
jovyanai_extension-0.3.1.data/data/share/jupyter/labextensions/@jovyanai/labextension/static/181.412a3027e9725e81a252.js
jovyanai_extension-0.3.1.data/data/share/jupyter/labextensions/@jovyanai/labextension/static/251.6b01f84ce480e9505e1b.js
jovyanai_extension-0.3.1.data/data/share/jupyter/labextensions/@jovyanai/labextension/static/301.a1414412dc9cb001361f.js
jovyanai_extension-0.3.1.data/data/share/jupyter/labextensions/@jovyanai/labextension/static/379.7473d03c2d0255d6ebbc.js
jovyanai_extension-0.3.1.data/data/share/jupyter/labextensions/@jovyanai/labextension/static/411.f0f1a5cde2ca5be81145.js
jovyanai_extension-0.3.1.data/data/share/jupyter/labextensions/@jovyanai/labextension/static/411.f0f1a5cde2ca5be81145.js.LICENSE.txt
jovyanai_extension-0.3.1.data/data/share/jupyter/labextensions/@jovyanai/labextension/static/430.839790b251e36df496cc.js
jovyanai_extension-0.3.1.dist-info/METADATA
jovyanai_extension-0.3.1.dist-info/WHEEL
jovyanai_extension-0.3.1.dist-info/licenses/LICENSE
jovyanai_extension-0.3.1.dist-info/RECORD
