Metadata-Version: 2.4
Name: jovyanai_extension
Version: 0.3.1
Summary: A JupyterLab extension to integrate Jovyan AI
Project-URL: Homepage, https://github.com/jovyan-ai/jovyan-ai-extension
Project-URL: Bug Tracker, https://github.com/jovyan-ai/jovyan-ai-extension/issues
Project-URL: Repository, https://github.com/jovyan-ai/jovyan-ai-extension.git
Author-email: JovyanAI <contact@jovyan-ai.com>
License: BSD 3-Clause License
License-File: LICENSE
Keywords: jupyter,jupyterlab,jupyterlab-extension
Classifier: Framework :: Jupyter
Classifier: Framework :: Jupyter :: JupyterLab
Classifier: Framework :: Jupyter :: JupyterLab :: 4
Classifier: Framework :: Jupyter :: JupyterLab :: Extensions
Classifier: Framework :: Jupyter :: JupyterLab :: Extensions :: Prebuilt
Classifier: License :: OSI Approved :: BSD License
Classifier: Programming Language :: Python
Classifier: Programming Language :: Python :: 3
Classifier: Programming Language :: Python :: 3.9
Classifier: Programming Language :: Python :: 3.10
Classifier: Programming Language :: Python :: 3.11
Classifier: Programming Language :: Python :: 3.12
Classifier: Programming Language :: Python :: 3.13
Requires-Python: >=3.9
Requires-Dist: jupyterlab<5,>=4.0.0
Requires-Dist: requests>=2.20.0
